palourde/__init__.py
palourde/classes.py
palourde/cmdline.py
palourde-1.0.6.dist-info/METADATA
palourde-1.0.6.dist-info/WHEEL
palourde-1.0.6.dist-info/entry_points.txt
palourde-1.0.6.dist-info/licenses/LICENSE
palourde-1.0.6.dist-info/RECORD
