Metadata-Version: 2.1
Name: palourde
Version: 1.0.6
Summary: Converts v2.1 Postman Collections into Markdown Files
Project-URL: Homepage, https://github.com/bagabool/palourde
Author-email: Victor Martin <vicmartindev@gmail.com>
License-File: LICENSE
Classifier: License :: OSI Approved :: GNU General Public License v3 (GPLv3)
Classifier: Operating System :: OS Independent
Classifier: Programming Language :: Python :: 3
Requires-Python: >=3.10
Requires-Dist: dacite>=1.7.0
Requires-Dist: python-slugify>=7.0.0
